perustats/__init__.py
perustats/utils.py
perustats/version.py
perustats/BCRP/__init__.py
perustats/BCRP/fetcher.py
perustats/MTC/__init__.py
perustats/MTC/homologacion.py
perustats/MTC/test.py
perustats/inei/__init__.py
perustats/inei/constants.py
perustats/inei/fetcher.py
perustats/inei/utils.py
perustats-0.1.7.dist-info/licenses/LICENSE
perustats-0.1.7.dist-info/METADATA
perustats-0.1.7.dist-info/WHEEL
perustats-0.1.7.dist-info/top_level.txt
perustats-0.1.7.dist-info/RECORD
