Metadata-Version: 2.4
Name: perustats
Version: 0.1.7
Summary: Tools to download and process public datasets from Peru (INEI & BCRP).
Author-email: "Jhon K. Flores Rojas" <fr.jhonk@gmail.com>
License-Expression: Apache-2.0
Project-URL: Homepage, https://github.com/TJhon/PyPeruStats
Project-URL: Issues, https://github.com/TJhon/PyPeruStats/issues
Classifier: Programming Language :: Python :: 3
Classifier: Programming Language :: Python :: 3 :: Only
Classifier: Operating System :: OS Independent
Classifier: Intended Audience :: Developers
Classifier: Intended Audience :: Science/Research
Classifier: Topic :: Scientific/Engineering
Classifier: Topic :: Software Development :: Libraries
Requires-Python: >=3.9
License-File: LICENSE
Requires-Dist: bs4
Requires-Dist: httpx
Requires-Dist: joblib
Requires-Dist: lxml
Requires-Dist: pandas
Requires-Dist: requests
Requires-Dist: rich
Requires-Dist: tqdm
Requires-Dist: unidecode
Dynamic: license-file
